styler_middleware/__init__.py
styler_middleware/handle_exceptions.py
styler_middleware/handle_invalid_json.py
styler_middleware-0.4.0.dist-info/LICENSE
styler_middleware-0.4.0.dist-info/METADATA
styler_middleware-0.4.0.dist-info/WHEEL
styler_middleware-0.4.0.dist-info/top_level.txt
styler_middleware-0.4.0.dist-info/RECORD
