Metadata-Version: 2.1
Name: styler-middleware
Version: 0.4.0
Summary: Utility middlewares for aiohttp web apps.
Home-page: https://github.com/STYLER-Inc/styler-middleware
Author: Bruno Toshio Sugano
Author-email: bruno.sugano@styler.link
License: MIT license
Keywords: styler_middleware middleware aiohttp
Platform: UNKNOWN
Classifier: Development Status :: 2 - Pre-Alpha
Classifier: Intended Audience :: Developers
Classifier: License :: OSI Approved :: MIT License
Classifier: Natural Language :: English
Classifier: Programming Language :: Python :: 3
Classifier: Programming Language :: Python :: 3.8
Requires-Python: >=3.8
Requires-Dist: aiohttp
